Flask_Redis-0.3.0.dist-info/DESCRIPTION.rst
Flask_Redis-0.3.0.dist-info/METADATA
Flask_Redis-0.3.0.dist-info/RECORD
Flask_Redis-0.3.0.dist-info/WHEEL
Flask_Redis-0.3.0.dist-info/metadata.json
Flask_Redis-0.3.0.dist-info/top_level.txt
flask_redis/__init__.py
