Metadata-Version: 1.1
Name: Flask-Redis
Version: 0.3.0
Summary: Redis Extension for Flask Applications
Home-page: https://github.com/underyx/flask-redis
Author: Bence Nagy
Author-email: bence@underyx.me
License: UNKNOWN
Download-URL: https://github.com/underyx/flask-redis/releases
Platform: UNKNOWN
Classifier: Development Status :: 4 - Beta
Classifier: Environment :: Web Environment
Classifier: Framework :: Flask
Classifier: Intended Audience :: Developers
Classifier: License :: OSI Approved :: Apache Software License
Classifier: Operating System :: OS Independent
Classifier: Programming Language :: Python
Classifier: Programming Language :: Python :: 2
Classifier: Programming Language :: Python :: 2.7
Classifier: Programming Language :: Python :: 3
Classifier: Programming Language :: Python :: 3.5
Classifier: Topic :: Internet :: WWW/HTTP :: Dynamic Content
Classifier: Topic :: Software Development :: Libraries :: Python Modules
